GinVPN/GinSettings.py
GinVPN/__init__.py
GinVPN/gin_vpn_config.py
GinVPN/gin_vpn_server.py
GinVPN/AES/AES.py
GinVPN/AES/__init__.py
GinVPN/plugin/__init__.py
GinVPN/plugin/gin_vpn_plugin.py
GinVPN_Zokontech-0.1.1.dist-info/METADATA
GinVPN_Zokontech-0.1.1.dist-info/WHEEL
GinVPN_Zokontech-0.1.1.dist-info/entry_points.txt
GinVPN_Zokontech-0.1.1.dist-info/top_level.txt
GinVPN_Zokontech-0.1.1.dist-info/RECORD
