Metadata-Version: 2.1
Name: GinVPN-Zokontech
Version: 0.1.1
Summary: Psudo VPN using proxy.py
Home-page: UNKNOWN
Author: Zander Krasny
Author-email: akrasny@ufl.edu
License: UNKNOWN
Platform: UNKNOWN
Classifier: Programming Language :: Python :: 3
Classifier: License :: OSI Approved :: MIT License
Classifier: Operating System :: OS Independent
Requires-Python: >=3.8
Requires-Dist: proxy.py
Requires-Dist: aiohttp
